ofxstatement_vn_vietcombank-0.0.3-py3.9-nspkg.pth
ofxstatement/plugins/vietcombank_excel.py
ofxstatement_vn_vietcombank-0.0.3.dist-info/LICENSE
ofxstatement_vn_vietcombank-0.0.3.dist-info/METADATA
ofxstatement_vn_vietcombank-0.0.3.dist-info/WHEEL
ofxstatement_vn_vietcombank-0.0.3.dist-info/entry_points.txt
ofxstatement_vn_vietcombank-0.0.3.dist-info/namespace_packages.txt
ofxstatement_vn_vietcombank-0.0.3.dist-info/top_level.txt
ofxstatement_vn_vietcombank-0.0.3.dist-info/zip-safe
ofxstatement_vn_vietcombank-0.0.3.dist-info/RECORD
